[
  {
    "id": 24,
    "status": 1,
    "bake_id": 19,
    "quantity": 1,
    "created_at": "2021-11-16T22:53:30.295814",
    "updated_at": "2021-11-16T22:53:35.319941",
    "bake_order_id": 14,
    "price_at_order": 25000,
    "bake_created_at": "2021-11-16T03:41:23.211098",
    "bake_order_created_at": "2021-11-16T22:53:15.554477"
  },
  {
    "id": 40,
    "status": 1,
    "bake_id": 29,
    "quantity": 2,
    "created_at": "2021-11-25T08:10:25.673381",
    "updated_at": "2021-11-25T08:19:39.632468",
    "bake_order_id": 25,
    "price_at_order": 1000,
    "bake_created_at": "2021-11-25T02:41:01.585003",
    "bake_order_created_at": "2021-11-25T08:08:23.225782"
  },
  {
    "id": 25,
    "status": 1,
    "bake_id": 19,
    "quantity": 2,
    "created_at": "2021-11-16T23:22:24.788238",
    "updated_at": "2021-11-16T23:22:48.391478",
    "bake_order_id": 15,
    "price_at_order": 25000,
    "bake_created_at": "2021-11-16T03:41:23.211098",
    "bake_order_created_at": "2021-11-16T23:22:24.778478"
  },
  {
    "id": 39,
    "status": 1,
    "bake_id": 28,
    "quantity": 2,
    "created_at": "2021-11-25T08:08:23.238927",
    "updated_at": "2021-11-25T08:19:39.637071",
    "bake_order_id": 25,
    "price_at_order": 1200,
    "bake_created_at": "2021-11-24T11:45:33.325886",
    "bake_order_created_at": "2021-11-25T08:08:23.225782"
  },
  {
    "id": 6,
    "status": 1,
    "bake_id": 9,
    "quantity": 1,
    "created_at": "2021-11-14T09:58:19.058617",
    "updated_at": "2021-11-14T09:58:28.55639",
    "bake_order_id": 5,
    "price_at_order": 6500,
    "bake_created_at": "2021-11-14T09:09:20.0966",
    "bake_order_created_at": "2021-11-14T09:58:09.228732"
  },
  {
    "id": 41,
    "status": 1,
    "bake_id": 25,
    "quantity": 1,
    "created_at": "2021-11-25T08:20:32.16438",
    "updated_at": "2021-11-25T08:20:41.476061",
    "bake_order_id": 26,
    "price_at_order": 4000,
    "bake_created_at": "2021-11-24T11:11:52.063666",
    "bake_order_created_at": "2021-11-25T08:20:32.155833"
  },
  {
    "id": 16,
    "status": 3,
    "bake_id": 4,
    "quantity": 1,
    "created_at": "2021-11-16T03:53:24.172943",
    "updated_at": "2021-11-17T00:08:37.871152",
    "bake_order_id": 12,
    "price_at_order": 5400,
    "bake_created_at": "2021-11-12T06:52:14.990115",
    "bake_order_created_at": "2021-11-16T03:53:10.657356"
  },
  {
    "id": 26,
    "status": 0,
    "bake_id": 4,
    "quantity": 1,
    "created_at": "2021-11-19T15:55:17.315658",
    "updated_at": "2021-11-19T15:55:17.315658",
    "bake_order_id": 16,
    "price_at_order": null,
    "bake_created_at": "2021-11-12T06:52:14.990115",
    "bake_order_created_at": "2021-11-19T15:55:17.301877"
  },
  {
    "id": 27,
    "status": 0,
    "bake_id": 13,
    "quantity": 1,
    "created_at": "2021-11-19T15:55:31.859348",
    "updated_at": "2021-11-19T15:55:31.859348",
    "bake_order_id": 16,
    "price_at_order": null,
    "bake_created_at": "2021-11-15T02:32:58.06549",
    "bake_order_created_at": "2021-11-19T15:55:17.301877"
  },
  {
    "id": 8,
    "status": 1,
    "bake_id": 8,
    "quantity": 1,
    "created_at": "2021-11-14T10:14:41.049817",
    "updated_at": "2021-11-14T10:15:40.153785",
    "bake_order_id": 7,
    "price_at_order": 1000,
    "bake_created_at": "2021-11-14T06:44:09.928447",
    "bake_order_created_at": "2021-11-14T10:14:41.036444"
  },
  {
    "id": 15,
    "status": 3,
    "bake_id": 5,
    "quantity": 1,
    "created_at": "2021-11-16T03:53:10.675351",
    "updated_at": "2021-11-25T10:15:50.80212",
    "bake_order_id": 12,
    "price_at_order": 2400,
    "bake_created_at": "2021-11-12T07:24:56.676387",
    "bake_order_created_at": "2021-11-16T03:53:10.657356"
  },
  {
    "id": 2,
    "status": 3,
    "bake_id": 2,
    "quantity": 1,
    "created_at": "2021-11-11T14:47:36.321315",
    "updated_at": "2021-11-14T10:22:32.22032",
    "bake_order_id": 3,
    "price_at_order": 200,
    "bake_created_at": "2021-11-10T08:50:36.584162",
    "bake_order_created_at": "2021-11-11T14:47:36.30732"
  },
  {
    "id": 3,
    "status": 2,
    "bake_id": 2,
    "quantity": 1,
    "created_at": "2021-11-11T15:50:37.062445",
    "updated_at": "2021-11-14T10:22:45.988563",
    "bake_order_id": 4,
    "price_at_order": 200,
    "bake_created_at": "2021-11-10T08:50:36.584162",
    "bake_order_created_at": "2021-11-11T15:50:37.045322"
  },
  {
    "id": 4,
    "status": 4,
    "bake_id": 2,
    "quantity": 1,
    "created_at": "2021-11-14T09:58:09.248198",
    "updated_at": "2021-11-14T10:22:54.014732",
    "bake_order_id": 5,
    "price_at_order": 200,
    "bake_created_at": "2021-11-10T08:50:36.584162",
    "bake_order_created_at": "2021-11-14T09:58:09.228732"
  },
  {
    "id": 5,
    "status": 2,
    "bake_id": 8,
    "quantity": 1,
    "created_at": "2021-11-14T09:58:12.394161",
    "updated_at": "2021-11-14T10:23:05.765028",
    "bake_order_id": 5,
    "price_at_order": 1000,
    "bake_created_at": "2021-11-14T06:44:09.928447",
    "bake_order_created_at": "2021-11-14T09:58:09.228732"
  },
  {
    "id": 9,
    "status": 2,
    "bake_id": 10,
    "quantity": 1,
    "created_at": "2021-11-14T10:21:50.135163",
    "updated_at": "2021-11-14T10:24:51.145975",
    "bake_order_id": 8,
    "price_at_order": 3000,
    "bake_created_at": "2021-11-14T10:18:54.263147",
    "bake_order_created_at": "2021-11-14T10:21:50.126096"
  },
  {
    "id": 28,
    "status": 1,
    "bake_id": 22,
    "quantity": 1,
    "created_at": "2021-11-22T10:33:44.665257",
    "updated_at": "2021-11-22T10:37:33.386805",
    "bake_order_id": 17,
    "price_at_order": 8600,
    "bake_created_at": "2021-11-19T15:42:45.41987",
    "bake_order_created_at": "2021-11-22T10:33:44.648674"
  },
  {
    "id": 11,
    "status": 1,
    "bake_id": 10,
    "quantity": 2,
    "created_at": "2021-11-14T10:24:35.920722",
    "updated_at": "2021-11-14T10:24:53.438751",
    "bake_order_id": 9,
    "price_at_order": 3000,
    "bake_created_at": "2021-11-14T10:18:54.263147",
    "bake_order_created_at": "2021-11-14T10:24:23.816203"
  },
  {
    "id": 29,
    "status": 1,
    "bake_id": 2,
    "quantity": 6,
    "created_at": "2021-11-22T10:33:53.198732",
    "updated_at": "2021-11-22T10:37:33.392478",
    "bake_order_id": 17,
    "price_at_order": 200,
    "bake_created_at": "2021-11-10T08:50:36.584162",
    "bake_order_created_at": "2021-11-22T10:33:44.648674"
  },
  {
    "id": 7,
    "status": 1,
    "bake_id": 8,
    "quantity": 6,
    "created_at": "2021-11-14T09:59:40.696083",
    "updated_at": "2021-11-14T10:47:14.078704",
    "bake_order_id": 6,
    "price_at_order": 1000,
    "bake_created_at": "2021-11-14T06:44:09.928447",
    "bake_order_created_at": "2021-11-14T09:59:40.675818"
  },
  {
    "id": 12,
    "status": 1,
    "bake_id": 11,
    "quantity": 1,
    "created_at": "2021-11-14T10:49:26.481207",
    "updated_at": "2021-11-14T10:49:54.185212",
    "bake_order_id": 10,
    "price_at_order": 30500,
    "bake_created_at": "2021-11-14T10:47:34.189734",
    "bake_order_created_at": "2021-11-14T10:49:26.471942"
  },
  {
    "id": 10,
    "status": 3,
    "bake_id": 1,
    "quantity": 1,
    "created_at": "2021-11-14T10:24:23.841712",
    "updated_at": "2021-11-14T10:52:54.040214",
    "bake_order_id": 9,
    "price_at_order": 5400,
    "bake_created_at": "2021-11-10T08:43:16.691172",
    "bake_order_created_at": "2021-11-14T10:24:23.816203"
  },
  {
    "id": 13,
    "status": 1,
    "bake_id": 12,
    "quantity": 1,
    "created_at": "2021-11-14T11:00:12.665623",
    "updated_at": "2021-11-14T11:00:38.145786",
    "bake_order_id": 11,
    "price_at_order": 89100,
    "bake_created_at": "2021-11-14T10:48:45.536608",
    "bake_order_created_at": "2021-11-14T11:00:12.641199"
  },
  {
    "id": 14,
    "status": 1,
    "bake_id": 11,
    "quantity": 1,
    "created_at": "2021-11-14T11:00:17.596293",
    "updated_at": "2021-11-14T11:00:38.176724",
    "bake_order_id": 11,
    "price_at_order": 30500,
    "bake_created_at": "2021-11-14T10:47:34.189734",
    "bake_order_created_at": "2021-11-14T11:00:12.641199"
  },
  {
    "id": 1,
    "status": 4,
    "bake_id": 3,
    "quantity": 1,
    "created_at": "2021-11-11T14:39:22.304934",
    "updated_at": "2021-11-14T11:11:44.011529",
    "bake_order_id": 1,
    "price_at_order": 30000,
    "bake_created_at": "2021-11-10T13:16:21.474385",
    "bake_order_created_at": "2021-11-11T14:39:22.286569"
  },
  {
    "id": 30,
    "status": 2,
    "bake_id": 4,
    "quantity": 2,
    "created_at": "2021-11-22T10:38:22.388645",
    "updated_at": "2021-11-22T10:39:24.813528",
    "bake_order_id": 18,
    "price_at_order": 5400,
    "bake_created_at": "2021-11-12T06:52:14.990115",
    "bake_order_created_at": "2021-11-22T10:38:22.379496"
  },
  {
    "id": 17,
    "status": 1,
    "bake_id": 13,
    "quantity": 1,
    "created_at": "2021-11-16T03:53:37.358549",
    "updated_at": "2021-11-16T03:53:54.422326",
    "bake_order_id": 12,
    "price_at_order": 15000,
    "bake_created_at": "2021-11-15T02:32:58.06549",
    "bake_order_created_at": "2021-11-16T03:53:10.657356"
  },
  {
    "id": 18,
    "status": 1,
    "bake_id": 21,
    "quantity": 1,
    "created_at": "2021-11-16T14:18:04.702239",
    "updated_at": "2021-11-16T14:18:48.76023",
    "bake_order_id": 13,
    "price_at_order": 10000,
    "bake_created_at": "2021-11-16T03:51:58.605644",
    "bake_order_created_at": "2021-11-16T14:18:04.467652"
  },
  {
    "id": 19,
    "status": 1,
    "bake_id": 9,
    "quantity": 1,
    "created_at": "2021-11-16T14:18:10.535123",
    "updated_at": "2021-11-16T14:18:48.77545",
    "bake_order_id": 13,
    "price_at_order": 6500,
    "bake_created_at": "2021-11-14T09:09:20.0966",
    "bake_order_created_at": "2021-11-16T14:18:04.467652"
  },
  {
    "id": 31,
    "status": 1,
    "bake_id": 10,
    "quantity": 2,
    "created_at": "2021-11-24T10:49:22.061325",
    "updated_at": "2021-11-24T10:49:44.384673",
    "bake_order_id": 19,
    "price_at_order": 3000,
    "bake_created_at": "2021-11-14T10:18:54.263147",
    "bake_order_created_at": "2021-11-24T10:49:22.045308"
  },
  {
    "id": 20,
    "status": 1,
    "bake_id": 10,
    "quantity": 1,
    "created_at": "2021-11-16T14:18:18.594982",
    "updated_at": "2021-11-16T14:18:48.785683",
    "bake_order_id": 13,
    "price_at_order": 3000,
    "bake_created_at": "2021-11-14T10:18:54.263147",
    "bake_order_created_at": "2021-11-16T14:18:04.467652"
  },
  {
    "id": 21,
    "status": 1,
    "bake_id": 20,
    "quantity": 1,
    "created_at": "2021-11-16T14:18:25.528197",
    "updated_at": "2021-11-16T14:18:48.799447",
    "bake_order_id": 13,
    "price_at_order": 2000,
    "bake_created_at": "2021-11-16T03:43:00.517062",
    "bake_order_created_at": "2021-11-16T14:18:04.467652"
  },
  {
    "id": 22,
    "status": 1,
    "bake_id": 19,
    "quantity": 1,
    "created_at": "2021-11-16T14:18:32.959363",
    "updated_at": "2021-11-16T14:18:48.805435",
    "bake_order_id": 13,
    "price_at_order": 25000,
    "bake_created_at": "2021-11-16T03:41:23.211098",
    "bake_order_created_at": "2021-11-16T14:18:04.467652"
  },
  {
    "id": 33,
    "status": 3,
    "bake_id": 24,
    "quantity": 1,
    "created_at": "2021-11-24T11:38:54.251176",
    "updated_at": "2021-11-24T11:40:26.105812",
    "bake_order_id": 21,
    "price_at_order": 2500,
    "bake_created_at": "2021-11-24T10:40:48.182836",
    "bake_order_created_at": "2021-11-24T11:38:54.239239"
  },
  {
    "id": 36,
    "status": 1,
    "bake_id": 27,
    "quantity": 2,
    "created_at": "2021-11-24T20:11:34.870225",
    "updated_at": "2021-11-24T20:11:51.021079",
    "bake_order_id": 23,
    "price_at_order": 8000,
    "bake_created_at": "2021-11-24T11:34:55.45345",
    "bake_order_created_at": "2021-11-24T20:11:08.135052"
  },
  {
    "id": 37,
    "status": 3,
    "bake_id": 1,
    "quantity": 1,
    "created_at": "2021-11-25T02:37:14.164039",
    "updated_at": "2021-11-25T04:41:05.749446",
    "bake_order_id": 24,
    "price_at_order": 5400,
    "bake_created_at": "2021-11-10T08:43:16.691172",
    "bake_order_created_at": "2021-11-25T02:37:14.1461"
  },
  {
    "id": 38,
    "status": 1,
    "bake_id": 27,
    "quantity": 2,
    "created_at": "2021-11-25T06:23:02.4778",
    "updated_at": "2021-11-25T08:06:52.690454",
    "bake_order_id": 22,
    "price_at_order": 8000,
    "bake_created_at": "2021-11-24T11:34:55.45345",
    "bake_order_created_at": "2021-11-24T12:10:59.136456"
  }
]
